deeposlandia/__init__.py
deeposlandia/__main__.py
deeposlandia/aggregate_label.py
deeposlandia/datagen.py
deeposlandia/feature_detection.py
deeposlandia/generator.py
deeposlandia/geoinference.py
deeposlandia/geometries.py
deeposlandia/inference.py
deeposlandia/metrics.py
deeposlandia/network.py
deeposlandia/postprocess.py
deeposlandia/semantic_segmentation.py
deeposlandia/train.py
deeposlandia/utils.py
deeposlandia/datasets/__init__.py
deeposlandia/datasets/aerial.py
deeposlandia/datasets/mapillary.py
deeposlandia/datasets/shapes.py
deeposlandia/datasets/tanzania.py
deeposlandia/webapp/__init__.py
deeposlandia/webapp/main.py
deeposlandia/webapp/run.py
deeposlandia/webapp/wsgi.py
tests/__init__.py
tests/conftest.py
tests/test_cnn_model.py
tests/test_dataset.py
tests/test_feature_detection.py
tests/test_generators.py
tests/test_geoinference.py
tests/test_geometries.py
tests/test_model_training.py
tests/test_path.py
tests/test_postprocess.py
tests/test_semantic_segmentation.py
deeposlandia-0.8.0.dist-info/LICENSE.md
deeposlandia-0.8.0.dist-info/METADATA
deeposlandia-0.8.0.dist-info/WHEEL
deeposlandia-0.8.0.dist-info/entry_points.txt
deeposlandia-0.8.0.dist-info/top_level.txt
deeposlandia-0.8.0.dist-info/RECORD
