Metadata-Version: 2.1
Name: deeposlandia
Version: 0.8.0
Summary: Automatic detection and semantic image segmentation with deep learning
Home-page: https://github.com/Oslandia/deeposlandia
Author: Oslandia
Author-email: info@oslandia.com
Maintainer: Oslandia
Maintainer-email: 
License: MIT
Keywords: deep learning,convolutional neural networks,image,Keras
Platform: UNKNOWN
Classifier: Development Status :: 4 - Beta
Classifier: Intended Audience :: Developers
Classifier: Intended Audience :: Science/Research
Classifier: Topic :: Scientific/Engineering :: Artificial Intelligence
Classifier: Operating System :: OS Independent
Classifier: License :: OSI Approved :: MIT License
Classifier: Programming Language :: Python :: 3.5
Classifier: Programming Language :: Python :: 3.6
Classifier: Programming Language :: Python :: Implementation :: CPython
Requires-Python: >=3
License-File: LICENSE.md
